postgresql_server_mcp/__init__.py
postgresql_server_mcp/server.py
postgresql_server_mcp-0.1.3.dist-info/METADATA
postgresql_server_mcp-0.1.3.dist-info/WHEEL
postgresql_server_mcp-0.1.3.dist-info/entry_points.txt
postgresql_server_mcp-0.1.3.dist-info/RECORD
