Metadata-Version: 2.4
Name: postgresql-server-mcp
Version: 0.1.3
Summary: A simplified PostgreSQL MCP server
Requires-Python: >=3.10
Requires-Dist: mcp[cli]>=1.0.0
Requires-Dist: psycopg[binary]>=3.2.0
